batchout/__init__.py
batchout/cli.py
batchout/core/__init__.py
batchout/core/batch.py
batchout/core/config.py
batchout/core/data.py
batchout/core/registry.py
batchout/core/util.py
batchout/ext/__init__.py
batchout/ext/jsonpath/__init__.py
batchout/ext/jsonpath/extractors.py
batchout/ext/postgres/__init__.py
batchout/ext/postgres/inputs.py
batchout/ext/postgres/outputs.py
batchout/ext/xpath/__init__.py
batchout/ext/xpath/extractors.py
batchout/std/__init__.py
batchout/std/columns/__init__.py
batchout/std/columns/base.py
batchout/std/columns/mixin.py
batchout/std/columns/scalar.py
batchout/std/extractors/__init__.py
batchout/std/extractors/base.py
batchout/std/extractors/mixin.py
batchout/std/extractors/regex.py
batchout/std/indexes/__init__.py
batchout/std/indexes/base.py
batchout/std/indexes/scalar.py
batchout/std/inputs/__init__.py
batchout/std/inputs/base.py
batchout/std/inputs/const.py
batchout/std/inputs/file.py
batchout/std/inputs/http.py
batchout/std/outputs/__init__.py
batchout/std/outputs/base.py
batchout/std/outputs/csv.py
batchout/std/outputs/logger.py
batchout/std/processors/__init__.py
batchout/std/processors/base.py
batchout/std/processors/pure.py
batchout/std/selectors/__init__.py
batchout/std/selectors/base.py
batchout/std/selectors/sql.py
batchout/std/tasks/__init__.py
batchout/std/tasks/base.py
batchout/std/tasks/reader.py
batchout/std/tasks/writer.py
batchout-0.3.0.dist-info/LICENSE
batchout-0.3.0.dist-info/METADATA
batchout-0.3.0.dist-info/WHEEL
batchout-0.3.0.dist-info/entry_points.txt
batchout-0.3.0.dist-info/top_level.txt
batchout-0.3.0.dist-info/RECORD
