Metadata-Version: 2.1
Name: batchout
Version: 0.3.0
Summary: Framework for building data pipelines
Home-page: https://github.com/ilia-khaustov/batchout
Author: Ilia Khaustov
Classifier: Programming Language :: Python :: 3
Classifier: License :: OSI Approved :: MIT License
Requires-Python: >=3.9
License-File: LICENSE
Provides-Extra: cli
Requires-Dist: pyyaml (==6.0) ; extra == 'cli'
Provides-Extra: jsonpath
Requires-Dist: jsonpath-rw (==1.4.0) ; extra == 'jsonpath'
Provides-Extra: postgres
Requires-Dist: psycopg (==3.0.14) ; extra == 'postgres'
Provides-Extra: xpath
Requires-Dist: lxml (==4.8.0) ; extra == 'xpath'
